Metadata-Version: 1.0
Name: textconverter
Version: 0.1.1
Summary: convert text encoding utility
Home-page: https://github.com/ukyo/textconverter
Author: ukyo
Author-email: ukyo.web@gmail.com
License: Apache
Keywords: text encoding convert
Platform: UNKNOWN
